README.md
setup.py
sysprl412/__init__.py
sysprl412/sysprl412.py
sysprl412.egg-info/PKG-INFO
sysprl412.egg-info/SOURCES.txt
sysprl412.egg-info/dependency_links.txt
sysprl412.egg-info/requires.txt
sysprl412.egg-info/top_level.txt