Metadata-Version: 1.0
Name: sysprl412
Version: 0.1
Summary: Consume API
Home-page: UNKNOWN
Author: n4ss4u
Author-email: UNKNOWN
License: UNKNOWN
Platform: UNKNOWN
